basecrm/__init__.py
basecrm/apps.py
basecrm/exceptions.py
basecrm/helpers.py
basecrm/serializers.py
basecrm/settings.py
basecrm/tests.py
basecrm/utils.py
django_basecrm-0.7.dist-info/LICENSE
django_basecrm-0.7.dist-info/METADATA
django_basecrm-0.7.dist-info/WHEEL
django_basecrm-0.7.dist-info/top_level.txt
django_basecrm-0.7.dist-info/RECORD
